{
  "number": "087",
  "periods": [
    {
      "start": "2024-06-22"
    }
  ],
  "category": "media-interview",
  "visibility": "public",
  "status": "done",
  "experienceTags": [
    "presentation",
    "reflection"
  ],
  "projectDomains": [],
  "techTags": [],
  "related": [
    {
      "number": "086",
      "relation": "related",
      "note": {
        "ko": "발표 세션이 포함된 행사",
        "en": "Event that included the talk session"
      }
    }
  ],
  "representativeImage": {
    "src": "/experience/images/experiences/087/representative.jpg",
    "alt": {
      "ko": "2024 SSAFYnale 발표 세션 대표 이미지",
      "en": "Representative image for the 2024 SSAFYnale presentation session"
    }
  },
  "featured": false
}
